actionrules/__init__.py
actionrules/actionRules/__init__.py
actionrules/actionRules/actionRules.py
actionrules/actionRulesDiscovery/__init__.py
actionrules/actionRulesDiscovery/actionRulesDiscovery.py
actionrules/decisions/__init__.py
actionrules/decisions/decisions.py
actionrules/desiredState/__init__.py
actionrules/desiredState/desiredState.py
actionrules/reduction/__init__.py
actionrules/reduction/reduction.py
actionrules/utilityMining/__init__.py
actionrules/utilityMining/utilityMining.py
actionrules_lukassykora-1.1.27.dist-info/METADATA
actionrules_lukassykora-1.1.27.dist-info/WHEEL
actionrules_lukassykora-1.1.27.dist-info/top_level.txt
actionrules_lukassykora-1.1.27.dist-info/RECORD
