Metadata-Version: 2.1
Name: actionrules-lukassykora
Version: 1.1.27
Summary: Action rules mining package
Home-page: https://github.com/lukassykora/actionrules
Author: Lukas Sykora
Author-email: lukassykora@seznam.cz
Classifier: Programming Language :: Python :: 3
Classifier: License :: OSI Approved :: MIT License
Classifier: Operating System :: OS Independent
Requires-Python: >=3.6
Requires-Dist: pandas
Requires-Dist: numpy
Requires-Dist: pyfim
